xz/__init__.py
xz/_version.py
xz/block.py
xz/common.py
xz/file.py
xz/io.py
xz/open.py
xz/py.typed
xz/strategy.py
xz/stream.py
xz/typing.py
xz/utils.py
python_xz-0.6.0.dist-info/METADATA
python_xz-0.6.0.dist-info/WHEEL
python_xz-0.6.0.dist-info/licenses/LICENSE.txt
python_xz-0.6.0.dist-info/RECORD
