Metadata-Version: 2.4
Name: python-xz
Version: 0.6.0
Summary: Pure Python implementation of the XZ file format with random access support
Project-URL: Homepage, https://github.com/rogdham/python-xz
Project-URL: Source, https://github.com/rogdham/python-xz
Author-email: Rogdham <contact@rogdham.net>
License-Expression: MIT
License-File: LICENSE.txt
Keywords: compression,decompression,lzma,xz
Classifier: Development Status :: 3 - Alpha
Classifier: Operating System :: OS Independent
Classifier: Programming Language :: Python
Classifier: Programming Language :: Python :: 3
Classifier: Programming Language :: Python :: 3 :: Only
Classifier: Programming Language :: Python :: 3.10
Classifier: Programming Language :: Python :: 3.11
Classifier: Programming Language :: Python :: 3.12
Classifier: Programming Language :: Python :: 3.13
Classifier: Programming Language :: Python :: 3.14
Classifier: Topic :: System :: Archiving
Classifier: Topic :: System :: Archiving :: Compression
Classifier: Topic :: Utilities
Requires-Python: >=3.10
